graphene_django_graphiql_static/__init__.py
graphene_django_graphiql_static/admin.py
graphene_django_graphiql_static/apps.py
graphene_django_graphiql_static/models.py
graphene_django_graphiql_static/urls.py
graphene_django_graphiql_static/views.py
graphene_django_graphiql_static/static/graphene_django_graphiql_static/fetch.umd.js
graphene_django_graphiql_static/static/graphene_django_graphiql_static/graphiql-plugin-explorer.umd.js
graphene_django_graphiql_static/static/graphene_django_graphiql_static/graphiql.min.css
graphene_django_graphiql_static/static/graphene_django_graphiql_static/graphiql.min.js
graphene_django_graphiql_static/static/graphene_django_graphiql_static/graphql-ws.min.js
graphene_django_graphiql_static/static/graphene_django_graphiql_static/react-dom.production.min.js
graphene_django_graphiql_static/static/graphene_django_graphiql_static/react.production.min.js
graphene_django_graphiql_static/static/graphene_django_graphiql_static/style.css
graphene_django_graphiql_static/templates/graphene_django_graphiql_static/graphiql_mod.html
graphene_django_graphiql_static/test_utils/__init__.py
graphene_django_graphiql_static/test_utils/test_app/__init__.py
graphene_django_graphiql_static/test_utils/test_app/admin.py
graphene_django_graphiql_static/test_utils/test_app/apps.py
graphene_django_graphiql_static/test_utils/test_app/models.py
graphene_django_graphiql_static/test_utils/test_app/migrations/__init__.py
graphene_django_graphiql_static-0.8.dist-info/AUTHORS.rst
graphene_django_graphiql_static-0.8.dist-info/LICENSE
graphene_django_graphiql_static-0.8.dist-info/METADATA
graphene_django_graphiql_static-0.8.dist-info/WHEEL
graphene_django_graphiql_static-0.8.dist-info/top_level.txt
graphene_django_graphiql_static-0.8.dist-info/RECORD
