Metadata-Version: 2.1
Name: graphene-django-graphiql-static
Version: 0.8
Summary: Offline-compatible GraphiQL for Graphene-Django
Author-email: Prashant Patel <prashantz7242@gmail.com>
Project-URL: Homepage, https://github.com/prashantz7242/graphene-django-graphiql-static/
Project-URL: Documentation, https://github.com/prashantz7242/graphene-django-graphiql-static#readme
Classifier: Environment :: Web Environment
Classifier: Framework :: Django
Classifier: Framework :: Django :: 4.2
Classifier: Intended Audience :: Developers
Classifier: License :: OSI Approved :: BSD License
Classifier: Operating System :: OS Independent
Classifier: Programming Language :: Python
Classifier: Programming Language :: Python :: 3
Classifier: Programming Language :: Python :: 3 :: Only
Classifier: Programming Language :: Python :: 3.10
Classifier: Programming Language :: Python :: 3.11
Classifier: Programming Language :: Python :: 3.12
Classifier: Programming Language :: Python :: 3.13
Classifier: Topic :: Internet :: WWW/HTTP
Classifier: Topic :: Internet :: WWW/HTTP :: Dynamic Content
Requires-Python: >=3.10
License-File: LICENSE
License-File: AUTHORS.rst
